.gitignore
.pylintrc
.readthedocs.yml
.travis.yml
CODE_OF_CONDUCT.md
LICENSE
README.rst
requirements.txt
setup.py
sparkfun_qwiictwist.py
adafruit_circuitpython_qwiictwist.egg-info/PKG-INFO
adafruit_circuitpython_qwiictwist.egg-info/SOURCES.txt
adafruit_circuitpython_qwiictwist.egg-info/dependency_links.txt
adafruit_circuitpython_qwiictwist.egg-info/requires.txt
adafruit_circuitpython_qwiictwist.egg-info/top_level.txt
docs/api.rst
docs/conf.py
docs/examples.rst
docs/index.rst
docs/_static/favicon.ico
examples/example10_i2c_scanner.py
examples/example1_basic_readings.py
examples/example2_set_color.py
examples/example3_crazy_color.py
examples/example4_connect_colors.py
examples/example5_timestamps.py
examples/example6_difference.py
examples/example7_set_count.py
examples/example8_interrupts.py
examples/example9_change_i2c_address.py
examples/qwiictwist_simpletest.py